{
    "aforo_zonas": [
        {
            "name": "CARDIO",
            "targetCapacity": 11,
            "totalCapacity": 70
        },
        {
            "name": "CIRCUIT",
            "targetCapacity": 4,
            "totalCapacity": 10
        },
        {
            "name": "ISOTONICO",
            "targetCapacity": 26,
            "totalCapacity": 32
        },
        {
            "name": "FUNCIONAL",
            "targetCapacity": 2,
            "totalCapacity": 12
        },
        {
            "name": "PESO LIBRE",
            "targetCapacity": 39,
            "totalCapacity": 50
        },
        {
            "name": "CORE",
            "targetCapacity": 3,
            "totalCapacity": 20
        },
        {
            "name": "X-TRAINING",
            "targetCapacity": 13,
            "totalCapacity": 24
        },
        {
            "name": "PP",
            "targetCapacity": 0,
            "totalCapacity": 25
        },
        {
            "name": "PG",
            "targetCapacity": 7,
            "totalCapacity": 42
        },
        {
            "name": "SAUNA",
            "targetCapacity": 4,
            "totalCapacity": 15
        },
        {
            "name": "BANO VAPOR",
            "targetCapacity": 2,
            "totalCapacity": 15
        },
        {
            "name": "PP EXT.",
            "targetCapacity": 0,
            "totalCapacity": 15
        },
        {
            "name": "SOLARIUM",
            "targetCapacity": 0,
            "totalCapacity": 30
        },
        {
            "name": "DESCANSO",
            "targetCapacity": 1,
            "totalCapacity": 25
        }
    ]
}